mseep_powerpoint-0.1.4.dist-info/licenses/LICENSE
powerpoint/__init__.py
powerpoint/chart_manager.py
powerpoint/presentation_manager.py
powerpoint/server.py
powerpoint/vision_manager.py
mseep_powerpoint-0.1.4.dist-info/METADATA
mseep_powerpoint-0.1.4.dist-info/WHEEL
mseep_powerpoint-0.1.4.dist-info/entry_points.txt
mseep_powerpoint-0.1.4.dist-info/top_level.txt
mseep_powerpoint-0.1.4.dist-info/RECORD
